openedx_authz/__init__.py
openedx_authz/admin.py
openedx_authz/apps.py
openedx_authz/handlers.py
openedx_authz/urls.py
openedx_authz/api/__init__.py
openedx_authz/api/data.py
openedx_authz/api/permissions.py
openedx_authz/api/roles.py
openedx_authz/api/users.py
openedx_authz/constants/__init__.py
openedx_authz/constants/permissions.py
openedx_authz/constants/roles.py
openedx_authz/engine/__init__.py
openedx_authz/engine/adapter.py
openedx_authz/engine/apps.py
openedx_authz/engine/enforcer.py
openedx_authz/engine/filter.py
openedx_authz/engine/matcher.py
openedx_authz/engine/utils.py
openedx_authz/engine/config/authz.policy
openedx_authz/engine/config/model.conf
openedx_authz/management/__init__.py
openedx_authz/management/commands/__init__.py
openedx_authz/management/commands/enforcement.py
openedx_authz/management/commands/load_policies.py
openedx_authz/migrations/0001_add_casbin_dependency.py
openedx_authz/migrations/0002_initial.py
openedx_authz/migrations/0003_usersubject.py
openedx_authz/migrations/0004_contentlibraryscope.py
openedx_authz/migrations/__init__.py
openedx_authz/models/__init__.py
openedx_authz/models/core.py
openedx_authz/models/scopes.py
openedx_authz/models/subjects.py
openedx_authz/rest_api/__init__.py
openedx_authz/rest_api/data.py
openedx_authz/rest_api/decorators.py
openedx_authz/rest_api/urls.py
openedx_authz/rest_api/utils.py
openedx_authz/rest_api/v1/__init__.py
openedx_authz/rest_api/v1/fields.py
openedx_authz/rest_api/v1/paginators.py
openedx_authz/rest_api/v1/permissions.py
openedx_authz/rest_api/v1/serializers.py
openedx_authz/rest_api/v1/urls.py
openedx_authz/rest_api/v1/views.py
openedx_authz/settings/__init__.py
openedx_authz/settings/common.py
openedx_authz/settings/production.py
openedx_authz/settings/test.py
openedx_authz/templates/openedx_authz/base.html
openedx_authz/tests/api/__init__.py
openedx_authz/tests/api/test_data.py
openedx_authz/tests/api/test_roles.py
openedx_authz/tests/api/test_users.py
openedx_authz-0.17.1.dist-info/licenses/LICENSE
openedx_authz-0.17.1.dist-info/METADATA
openedx_authz-0.17.1.dist-info/WHEEL
openedx_authz-0.17.1.dist-info/entry_points.txt
openedx_authz-0.17.1.dist-info/top_level.txt
openedx_authz-0.17.1.dist-info/RECORD
