Metadata-Version: 2.4
Name: openedx-authz
Version: 0.17.1
Summary: Open edX AuthZ provides the architecture and foundations of the authorization framework.
Home-page: https://github.com/openedx/openedx-authz
Author: Open edX Project
Author-email: oscm@openedx.org
License: AGPL 3.0
Keywords: Python edx
Classifier: Development Status :: 3 - Alpha
Classifier: Framework :: Django
Classifier: Framework :: Django :: 4.2
Classifier: Framework :: Django :: 5.2
Classifier: Intended Audience :: Developers
Classifier: License :: OSI Approved :: GNU Affero General Public License v3 or later (AGPLv3+)
Classifier: Natural Language :: English
Classifier: Programming Language :: Python :: 3
Classifier: Programming Language :: Python :: 3.11
Classifier: Programming Language :: Python :: 3.12
Requires-Python: >=3.11
License-File: LICENSE
Requires-Dist: Django
Requires-Dist: attrs
Requires-Dist: casbin-django-orm-adapter
Requires-Dist: djangorestframework
Requires-Dist: edx-api-doc-tools
Requires-Dist: edx-drf-extensions
Requires-Dist: edx-opaque-keys
Requires-Dist: openedx-atlas
Requires-Dist: pycasbin
Dynamic: author
Dynamic: author-email
Dynamic: classifier
Dynamic: description
Dynamic: home-page
Dynamic: keywords
Dynamic: license
Dynamic: license-file
Dynamic: requires-dist
Dynamic: requires-python
Dynamic: summary
